mkvpy.py
smolog.py
mkvpy-0.0.2.dist-info/LICENSE
mkvpy-0.0.2.dist-info/METADATA
mkvpy-0.0.2.dist-info/WHEEL
mkvpy-0.0.2.dist-info/top_level.txt
mkvpy-0.0.2.dist-info/RECORD
