Metadata-Version: 2.1
Name: mkvpy
Version: 0.0.2
Summary: Python client for geohot/minikeyvalue key/value store.
Home-page: UNKNOWN
Author: Mateusz Bednarski
Author-email: msz.bednarski@gmail.com
License: UNKNOWN
Platform: UNKNOWN
Requires: requests
Requires-Python: >=3.6
License-File: LICENSE
